lakebench/__init__.py
lakebench/benchmarks/__init__.py
lakebench/benchmarks/base.py
lakebench/benchmarks/_load_and_query/__init__.py
lakebench/benchmarks/_load_and_query/_load_and_query.py
lakebench/benchmarks/clickbench/__init__.py
lakebench/benchmarks/clickbench/clickbench.py
lakebench/benchmarks/clickbench/engine_impl/__init__.py
lakebench/benchmarks/clickbench/engine_impl/duckdb.py
lakebench/benchmarks/clickbench/engine_impl/sail.py
lakebench/benchmarks/clickbench/engine_impl/spark.py
lakebench/benchmarks/clickbench/resources/ddl/__init__.py
lakebench/benchmarks/clickbench/resources/ddl/canonical/__init__.py
lakebench/benchmarks/clickbench/resources/ddl/canonical/ddl.sql
lakebench/benchmarks/clickbench/resources/queries/__init__.py
lakebench/benchmarks/clickbench/resources/queries/canonical/__init__.py
lakebench/benchmarks/clickbench/resources/queries/canonical/q1.sql
lakebench/benchmarks/clickbench/resources/queries/canonical/q10.sql
lakebench/benchmarks/clickbench/resources/queries/canonical/q11.sql
lakebench/benchmarks/clickbench/resources/queries/canonical/q12.sql
lakebench/benchmarks/clickbench/resources/queries/canonical/q13.sql
lakebench/benchmarks/clickbench/resources/queries/canonical/q14.sql
lakebench/benchmarks/clickbench/resources/queries/canonical/q15.sql
lakebench/benchmarks/clickbench/resources/queries/canonical/q16.sql
lakebench/benchmarks/clickbench/resources/queries/canonical/q17.sql
lakebench/benchmarks/clickbench/resources/queries/canonical/q18.sql
lakebench/benchmarks/clickbench/resources/queries/canonical/q19.sql
lakebench/benchmarks/clickbench/resources/queries/canonical/q2.sql
lakebench/benchmarks/clickbench/resources/queries/canonical/q20.sql
lakebench/benchmarks/clickbench/resources/queries/canonical/q21.sql
lakebench/benchmarks/clickbench/resources/queries/canonical/q22.sql
lakebench/benchmarks/clickbench/resources/queries/canonical/q23.sql
lakebench/benchmarks/clickbench/resources/queries/canonical/q24.sql
lakebench-0.13.2.dist-info/licenses/LICENSE
lakebench-0.13.2.dist-info/METADATA
lakebench-0.13.2.dist-info/WHEEL
lakebench-0.13.2.dist-info/top_level.txt
lakebench-0.13.2.dist-info/RECORD
