Metadata-Version: 2.4
Name: lakebench
Version: 0.13.2
Summary: A multi-modal Python library for benchmarking Azure lakehouse engines and ELT scenarios, supporting both industry-standard and novel benchmarks.
Author: Miles Cole
License: MIT License
Project-URL: github, https://github.com/mwc360/LakeBench
Project-URL: Issues, https://github.com/mwc360/LakeBench/issues
Classifier: Development Status :: 4 - Beta
Classifier: License :: OSI Approved :: MIT License
Classifier: Programming Language :: Python
Classifier: Intended Audience :: Developers
Classifier: Topic :: System :: Benchmark
Requires-Python: >=3.8
License-File: LICENSE
Requires-Dist: numpy>=1.24.4
Requires-Dist: sqlglot==26.30.0
Requires-Dist: fsspec>=2025.9.0
Requires-Dist: tenacity==9.1.2
Provides-Extra: duckdb
Requires-Dist: duckdb==1.4.1; extra == "duckdb"
Requires-Dist: deltalake==1.2.1; extra == "duckdb"
Requires-Dist: pyarrow>=15.0.0; extra == "duckdb"
Provides-Extra: polars
Requires-Dist: polars==1.34.0; extra == "polars"
Requires-Dist: deltalake==1.2.1; extra == "polars"
Requires-Dist: pyarrow>=15.0.0; extra == "polars"
Provides-Extra: daft
Requires-Dist: daft==0.6.6; extra == "daft"
Requires-Dist: deltalake==1.0.2; extra == "daft"
Requires-Dist: pyarrow>=15.0.0; extra == "daft"
Provides-Extra: tpcds-datagen
Requires-Dist: duckdb==1.4.1; extra == "tpcds-datagen"
Requires-Dist: pyarrow>=15.0.0; extra == "tpcds-datagen"
Provides-Extra: tpch-datagen
Requires-Dist: tpchgen-cli>=2.0.1; extra == "tpch-datagen"
Provides-Extra: sparkmeasure
Requires-Dist: sparkmeasure==0.24.0; extra == "sparkmeasure"
Provides-Extra: sail
Requires-Dist: pysail>=0.4.2; extra == "sail"
Requires-Dist: pyspark[connect]>=4.0.0; extra == "sail"
Requires-Dist: deltalake>=1.2.1; extra == "sail"
Requires-Dist: pyarrow>=15.0.0; extra == "sail"
Dynamic: license-file
